flask_dt.py
flask_dt-0.0.1.2.dist-info/LICENSE
flask_dt-0.0.1.2.dist-info/METADATA
flask_dt-0.0.1.2.dist-info/WHEEL
flask_dt-0.0.1.2.dist-info/top_level.txt
flask_dt-0.0.1.2.dist-info/RECORD
