Metadata-Version: 2.1
Name: flask-dt
Version: 0.0.1.2
Summary: Display Tables
Home-page: https://github.com/GreatDt1/flaskdt
Author: Donatus
Author-email: flaskdt@gmail.com
License: UNKNOWN
Platform: UNKNOWN
Classifier: Programming Language :: Python :: 3
Classifier: Programming Language :: Python :: 3.6
Classifier: Programming Language :: Python :: 3.7
Classifier: Programming Language :: Python :: 3.8
Classifier: Programming Language :: Python :: 3.9
Classifier: License :: OSI Approved :: MIT License
Classifier: Operating System :: OS Independent
Classifier: Development Status :: 4 - Beta
Classifier: Framework :: Flask
Classifier: Intended Audience :: Developers
Classifier: Intended Audience :: Education
Classifier: Natural Language :: English
Requires-Dist: SQLAlchemy (~=1.4.0)
Requires-Dist: Flask (~=2.0.1)
Requires-Dist: Flask-SQLAlchemy (~=2.5.1)
Provides-Extra: dev
Requires-Dist: pytest (>=3.7) ; extra == 'dev'
Requires-Dist: check-manifest (>=0.46) ; extra == 'dev'
Requires-Dist: twine (>=3.4.2) ; extra == 'dev'
